README.md
setup.py
foliant/cli/gupload.py
foliantcontrib.gupload.egg-info/PKG-INFO
foliantcontrib.gupload.egg-info/SOURCES.txt
foliantcontrib.gupload.egg-info/dependency_links.txt
foliantcontrib.gupload.egg-info/requires.txt
foliantcontrib.gupload.egg-info/top_level.txt