Metadata-Version: 2.1
Name: foliantcontrib.gupload
Version: 1.1.3
Summary: Documents to Google Drive uploader.
Home-page: https://github.com/foliant-docs/foliantcontrib.gupload
Author: Anton Bukhtiyarov
Author-email: apkraft@gmail.com
License: MIT
Platform: any
Classifier: Development Status :: 5 - Production/Stable
Classifier: Environment :: Console
Classifier: Intended Audience :: Developers
Classifier: License :: OSI Approved :: MIT License
Classifier: Operating System :: OS Independent
Classifier: Programming Language :: Python
Classifier: Topic :: Documentation
Classifier: Topic :: Utilities
